csvsmith/__init__.py
csvsmith/classify.py
csvsmith/cli.py
csvsmith/duplicates.py
csvsmith-0.2.0.dist-info/licenses/LICENSE
csvsmith-0.2.0.dist-info/METADATA
csvsmith-0.2.0.dist-info/WHEEL
csvsmith-0.2.0.dist-info/entry_points.txt
csvsmith-0.2.0.dist-info/top_level.txt
csvsmith-0.2.0.dist-info/RECORD
