Metadata-Version: 2.4
Name: csvsmith
Version: 0.2.0
Summary: Small CSV utilities: classification, duplicates, row digests, and CLI helpers.
Author-email: Eiichi YAMAMOTO <info@yeiichi.com>
License: MIT License
Project-URL: Homepage, https://github.com/yeiichi/csvsmith
Project-URL: Repository, https://github.com/yeiichi/csvsmith
Keywords: csv,pandas,duplicates,data-cleaning,file-organization
Classifier: Programming Language :: Python :: 3
Classifier: Programming Language :: Python :: 3 :: Only
Classifier: License :: OSI Approved :: MIT License
Classifier: Intended Audience :: Developers
Classifier: Topic :: Software Development :: Libraries
Classifier: Topic :: Utilities
Requires-Python: >=3.10
License-File: LICENSE
Requires-Dist: pandas>=2.0
Dynamic: license-file
